Metadata-Version: 2.1
Name: slack-signature-verifier
Version: 0.3
Summary: Verify your request from slack with your slack signing secret
Home-page: https://github.com/ebarnsli/slack_signature_verifier
Author: Erik Barns
Author-email: ebarns@labelinsight.com
License: MIT
Download-URL: https://github.com/ebarnsli/slack_signature_verifier/archive/0.0.5.tar.gz
Keywords: SLACK,SIGNING,SIGNATURE
Platform: UNKNOWN
Classifier: Development Status :: 3 - Alpha
Classifier: Topic :: Software Development :: Build Tools
Classifier: License :: OSI Approved :: MIT License
Classifier: Programming Language :: Python :: 3.7
